opentelemetry/py.typed
opentelemetry/tools/cloud_trace_propagator.py
opentelemetry/tools/resource_detector.py
opentelemetry/tools/google/version.py
opentelemetry_tools_google_cloud-0.18b1.dist-info/LICENSE
opentelemetry_tools_google_cloud-0.18b1.dist-info/METADATA
opentelemetry_tools_google_cloud-0.18b1.dist-info/WHEEL
opentelemetry_tools_google_cloud-0.18b1.dist-info/top_level.txt
opentelemetry_tools_google_cloud-0.18b1.dist-info/RECORD
