Metadata-Version: 2.1
Name: opentelemetry-tools-google-cloud
Version: 0.18b1
Summary: Deprecated Google Cloud propagator and resource detector for OpenTelemetry
Home-page: https://github.com/GoogleCloudPlatform/opentelemetry-operations-python/tree/master/opentelemetry-tools-google-cloud
Author: Google
Author-email: opentelemetry-pypi@google.com
License: Apache-2.0
Platform: any
Classifier: Development Status :: 4 - Beta
Classifier: Intended Audience :: Developers
Classifier: License :: OSI Approved :: Apache Software License
Classifier: Programming Language :: Python
Classifier: Programming Language :: Python :: 3
Classifier: Programming Language :: Python :: 3.5
Classifier: Programming Language :: Python :: 3.6
Classifier: Programming Language :: Python :: 3.7
Classifier: Programming Language :: Python :: 3.8
Requires-Python: >=3.5
Requires-Dist: google-auth (~=1.22)
Requires-Dist: opentelemetry-api (==0.17b0)
Requires-Dist: opentelemetry-sdk (==0.17b0)
Requires-Dist: requests (~=2.24)
Provides-Extra: test
